ddf_utils/__init__.py
ddf_utils/cli.py
ddf_utils/dsl.py
ddf_utils/i18n.py
ddf_utils/io.py
ddf_utils/package.py
ddf_utils/patch.py
ddf_utils/qa.py
ddf_utils/str.py
ddf_utils/transformer.py
ddf_utils/chef/__init__.py
ddf_utils/chef/api.py
ddf_utils/chef/exceptions.py
ddf_utils/chef/helpers.py
ddf_utils/chef/ops.py
ddf_utils/chef/hy_mod/__init__.py
ddf_utils/chef/model/__init__.py
ddf_utils/chef/model/chef.py
ddf_utils/chef/model/dag.py
ddf_utils/chef/model/ingredient.py
ddf_utils/chef/procedure/__init__.py
ddf_utils/chef/procedure/extract_concepts.py
ddf_utils/chef/procedure/filter.py
ddf_utils/chef/procedure/flatten.py
ddf_utils/chef/procedure/groupby.py
ddf_utils/chef/procedure/merge.py
ddf_utils/chef/procedure/merge_entity.py
ddf_utils/chef/procedure/run_op.py
ddf_utils/chef/procedure/split_entity.py
ddf_utils/chef/procedure/translate_column.py
ddf_utils/chef/procedure/translate_header.py
ddf_utils/chef/procedure/trend_bridge.py
ddf_utils/chef/procedure/window.py
ddf_utils/factory/__init__.py
ddf_utils/factory/clio_infra.py
ddf_utils/factory/common.py
ddf_utils/factory/ihme.py
ddf_utils/factory/ilo.py
ddf_utils/factory/oecd.py
ddf_utils/factory/worldbank.py
ddf_utils/model/__init__.py
ddf_utils/model/ddf.py
ddf_utils/model/package.py
ddf_utils/model/repo.py
ddf_utils/model/utils.py
ddf_utils-1.0.19.dist-info/licenses/LICENSE
ddf_utils-1.0.19.dist-info/METADATA
ddf_utils-1.0.19.dist-info/WHEEL
ddf_utils-1.0.19.dist-info/entry_points.txt
ddf_utils-1.0.19.dist-info/top_level.txt
ddf_utils-1.0.19.dist-info/RECORD
