Metadata-Version: 2.4
Name: ddf_utils
Version: 1.0.19
Summary: Commonly used functions/utilities for DDF file model.
Home-page: https://github.com/semio/ddf_utils
Author: Semio Zheng
Author-email: prairy.long@gmail.com
License: MIT
Keywords: etl,ddf,datasets,recipe
Classifier: Development Status :: 3 - Alpha
Classifier: Programming Language :: Python :: 3.10
Classifier: Programming Language :: Python :: 3.11
Classifier: Programming Language :: Python :: 3.12
Classifier: Programming Language :: Python :: 3.13
Classifier: Topic :: Utilities
License-File: LICENSE
Requires-Dist: pandas~=2.2.3
Requires-Dist: unidecode~=1.4.0
Requires-Dist: pyyaml~=6.0.2
Requires-Dist: orderedattrdict~=1.6.0
Requires-Dist: typing~=3.7.4.3
Requires-Dist: cookiecutter~=2.6.0
Requires-Dist: Click~=8.1.8
Requires-Dist: daff~=1.4.2
Requires-Dist: tabulate~=0.9.0
Requires-Dist: dask[dataframe]~=2025.4.1
Requires-Dist: tqdm~=4.67.1
Requires-Dist: ruamel.yaml~=0.18.10
Requires-Dist: graphviz~=0.20.3
Requires-Dist: coloredlogs~=15.0.1
Requires-Dist: pytz~=2025.2
Requires-Dist: requests[security]~=2.32.3
Requires-Dist: gitpython~=3.1.44
Requires-Dist: hy~=1.0.0
Requires-Dist: attrs~=25.3.0
Requires-Dist: joblib~=1.5.0
Requires-Dist: lxml~=5.4.0
Requires-Dist: pycurl~=7.45.6
Dynamic: author
Dynamic: author-email
Dynamic: classifier
Dynamic: description
Dynamic: home-page
Dynamic: keywords
Dynamic: license
Dynamic: license-file
Dynamic: requires-dist
Dynamic: summary
